vex/__init__.py
vex/constants.py
vex/package.py
vex/simplecve.py
vex/simplecvss.py
vex/simplenvd.py
vex/vex.py
vex/vex_reader.py
vex_reader-0.9.5.dist-info/licenses/LICENSE
vex_reader-0.9.5.dist-info/METADATA
vex_reader-0.9.5.dist-info/WHEEL
vex_reader-0.9.5.dist-info/entry_points.txt
vex_reader-0.9.5.dist-info/top_level.txt
vex_reader-0.9.5.dist-info/RECORD
