Metadata-Version: 2.4
Name: vex-reader
Version: 0.9.5
Summary: Read VEX files
Author-email: Vincent Danen <vdanen@annvix.com>
License:                     GNU GENERAL PUBLIC LICENSE
Project-URL: Homepage, https://github.com/vdanen/vex-reader
Project-URL: Issues, https://github.com/vdanen/vex-reader/issues
Classifier: Programming Language :: Python :: 3
Classifier: Development Status :: 4 - Beta
Classifier: License :: OSI Approved :: GNU General Public License v3 or later (GPLv3+)
Classifier: Operating System :: OS Independent
Requires-Python: >=3.9
License-File: LICENSE
Requires-Dist: requests==2.32.4
Requires-Dist: rich>=13.8.1
Requires-Dist: pytz>=2024.1
Provides-Extra: test
Requires-Dist: pytest==8.4.1; extra == "test"
Requires-Dist: pytest-cov==6.2.1; extra == "test"
Requires-Dist: pytest-xdist==3.8.0; extra == "test"
Requires-Dist: coverage==7.9.2; extra == "test"
Requires-Dist: flake8==7.3.0; extra == "test"
Requires-Dist: black==25.1.0; extra == "test"
Requires-Dist: build==1.2.1; extra == "test"
Requires-Dist: twine==6.1.0; extra == "test"
Requires-Dist: pkginfo==1.12.1.2; extra == "test"
Dynamic: license-file
